MANIFEST.in
setup.py
pentaho_deploy.egg-info/PKG-INFO
pentaho_deploy.egg-info/SOURCES.txt
pentaho_deploy.egg-info/dependency_links.txt
pentaho_deploy.egg-info/requires.txt
pentaho_deploy.egg-info/top_level.txt
pentahodeploy/__init__.py
pentahodeploy/fabfile.py
pentahodeploy/upstart-jobs/pentaho-biserver.conf
scripts/pentaho-deploy.sh