Metadata-Version: 1.0
Name: pentaho-deploy
Version: 0.1
Summary: Command line tools to help to install, deploy and configure Pentaho Softwares on Linux servers.
Home-page: UNKNOWN
Author: Sergio Oliveira
Author-email: seocam@seocam.com
License: UNKNOWN
Platform: UNKNOWN
Classifier: Development Status :: 3 - Alpha
Classifier: Environment :: Console
Classifier: Intended Audience :: System Administrators
Classifier: License :: OSI Approved :: GNU General Public License (GPL)
Classifier: Natural Language :: English
Classifier: Operating System :: POSIX :: Linux
Classifier: Programming Language :: Python
Classifier: Topic :: Software Development :: Libraries
Classifier: Topic :: System :: Systems Administration
Classifier: Topic :: Utilities
